claude_x/__init__.py
claude_x/analytics.py
claude_x/classifier.py
claude_x/cli.py
claude_x/context.py
claude_x/exceptions.py
claude_x/export.py
claude_x/extensions.py
claude_x/extractor.py
claude_x/filters.py
claude_x/i18n.py
claude_x/indexer.py
claude_x/mcp_server.py
claude_x/models.py
claude_x/pack_search.py
claude_x/patterns.py
claude_x/prompt_coach.py
claude_x/prompt_enhancer.py
claude_x/prompt_library.py
claude_x/prompt_templates.py
claude_x/py.typed
claude_x/scoring.py
claude_x/security.py
claude_x/session_parser.py
claude_x/storage.py
claude_x/template_matcher.py
claude_x/template_registry.py
claude_x/best_practices/__init__.py
claude_x/best_practices/code_review.yaml
claude_x/best_practices/coding_patterns.yaml
claude_x/best_practices/debugging.yaml
claude_x/best_practices/refactoring.yaml
claude_x/best_practices/registry.yaml
claude_x/best_practices/schema.py
claude_x-0.6.5.dist-info/METADATA
claude_x-0.6.5.dist-info/WHEEL
claude_x-0.6.5.dist-info/entry_points.txt
claude_x-0.6.5.dist-info/licenses/LICENSE
claude_x-0.6.5.dist-info/RECORD
