Metadata-Version: 2.4
Name: claude-x
Version: 0.6.5
Summary: Second Brain and Command Center for Claude Code
Project-URL: Homepage, https://github.com/kakao/claude-x
Project-URL: Documentation, https://github.com/kakao/claude-x#readme
Project-URL: Repository, https://github.com/kakao/claude-x
Project-URL: Issues, https://github.com/kakao/claude-x/issues
Project-URL: Changelog, https://github.com/kakao/claude-x/blob/main/CHANGELOG.md
Author-email: "lucas.ms" <karismalms@naver.com>
License: MIT
License-File: LICENSE
Keywords: ai,assistant,claude,claude-code,code-analysis,mcp,model-context-protocol,prompt-engineering,prompt-library,session-tracking
Classifier: Development Status :: 4 - Beta
Classifier: Intended Audience :: Developers
Classifier: License :: OSI Approved :: MIT License
Classifier: Programming Language :: Python :: 3
Classifier: Programming Language :: Python :: 3.10
Classifier: Programming Language :: Python :: 3.11
Classifier: Programming Language :: Python :: 3.12
Classifier: Programming Language :: Python :: 3.13
Classifier: Topic :: Software Development :: Libraries :: Python Modules
Classifier: Topic :: Utilities
Requires-Python: >=3.10
Requires-Dist: click>=8.1
Requires-Dist: mcp>=1.0.0
Requires-Dist: pydantic>=2.12.5
Requires-Dist: pyyaml>=6.0
Requires-Dist: rich>=14.2.0
Requires-Dist: typer>=0.21.1
Requires-Dist: watchdog>=6.0.0
